dg_sound_fuzz/__init__.py
dg_sound_fuzz/engine.py
dg_sound_fuzz/string.py
dg_sound_fuzz-0.1.5.dist-info/licenses/LICENSE
dg_sound_fuzz-0.1.5.dist-info/METADATA
dg_sound_fuzz-0.1.5.dist-info/WHEEL
dg_sound_fuzz-0.1.5.dist-info/top_level.txt
dg_sound_fuzz-0.1.5.dist-info/RECORD
