Metadata-Version: 2.4
Name: dg-sound-fuzz
Version: 0.1.5
Summary: A Python package for fuzzy string matching and name scoring using sound-based algorithms
Author-email: Narendrakumar G S <narendrakumar.gs@digitap.ai>, M V Pranav <pranav.mv@digitap.ai>, Sai Aditya Devulapalli <sai.aditya@digitap.ai>
License: MIT
Project-URL: Homepage, https://github.com/digitap/dg-sound-fuzz
Project-URL: Bug Tracker, https://github.com/digitap/dg-sound-fuzz/issues
Classifier: Development Status :: 4 - Beta
Classifier: Intended Audience :: Developers
Classifier: License :: OSI Approved :: MIT License
Classifier: Programming Language :: Python :: 3
Classifier: Programming Language :: Python :: 3.10
Classifier: Programming Language :: Python :: 3.11
Classifier: Programming Language :: Python :: 3.12
Requires-Python: >=3.10
License-File: LICENSE
Requires-Dist: RapidFuzz>=3.13.0
Requires-Dist: Metaphone~=0.6
Dynamic: license-file
